MANIFEST.in
README.md
README.txt
manage.py
setup.py
version
flask_xl.egg-info/PKG-INFO
flask_xl.egg-info/SOURCES.txt
flask_xl.egg-info/dependency_links.txt
flask_xl.egg-info/entry_points.txt
flask_xl.egg-info/not-zip-safe
flask_xl.egg-info/requires.txt
flask_xl.egg-info/top_level.txt
flask_xxl/__init__.py
flask_xxl/basemodels.py
flask_xxl/baseviews.py
flask_xxl/basewidgets.py
flask_xxl/cli.py
flask_xxl/filters.py
flask_xxl/hooks.py
flask_xxl/main.py
flask_xxl/manage.py
flask_xxl/mr_bob.py
flask_xxl/testing.py
flask_xxl/apps/__init__.py
flask_xxl/apps/__init__.pyc
flask_xxl/apps/admin/__init__.py
flask_xxl/apps/admin/__init__.pyc
flask_xxl/apps/admin/cfg.py
flask_xxl/apps/admin/forms.py
flask_xxl/apps/admin/forms.pyc
flask_xxl/apps/admin/models.py
flask_xxl/apps/admin/models.pyc
flask_xxl/apps/admin/urls.py
flask_xxl/apps/admin/urls.pyc
flask_xxl/apps/admin/utils.py
flask_xxl/apps/admin/views.py
flask_xxl/apps/admin/views.pyc
flask_xxl/apps/admin/templates/_macros.html
flask_xxl/apps/admin/templates/add.html
flask_xxl/apps/admin/templates/admin.html
flask_xxl/apps/admin/templates/dashboard.html
flask_xxl/apps/admin/templates/layout.html
flask_xxl/apps/admin/templates/list.html
flask_xxl/apps/admin/templates/list_pages.html
flask_xxl/apps/admin/templates/view_block.html
flask_xxl/apps/admin/templates/view_page.html
flask_xxl/apps/admin/templates/view_template.html
flask_xxl/apps/admin/templates/admin/_header.html
flask_xxl/apps/admin/templates/info/info_page.html
flask_xxl/apps/auth/__init__.py
flask_xxl/apps/auth/__init__.pyc
flask_xxl/apps/auth/context_processors.py
flask_xxl/apps/auth/filters.py
flask_xxl/apps/auth/forms.py
flask_xxl/apps/auth/forms.pyc
flask_xxl/apps/auth/models.py
flask_xxl/apps/auth/models.pyc
flask_xxl/apps/auth/urls.py
flask_xxl/apps/auth/urls.pyc
flask_xxl/apps/auth/utils.py
flask_xxl/apps/auth/utils.pyc
flask_xxl/apps/auth/views.py
flask_xxl/apps/auth/views.pyc
flask_xxl/apps/auth/templates/_bs3macros.html
flask_xxl/apps/auth/templates/_header.html
flask_xxl/apps/auth/templates/auth_login.html
flask_xxl/apps/auth/templates/dub.html
flask_xxl/apps/auth/templates/error.html
flask_xxl/apps/auth/templates/frontend_nav.html
flask_xxl/apps/auth/templates/header.html
