Metadata-Version: 1.0
Name: flask-xl
Version: 0.10.1
Summary: quick way to design large flask projects
Home-page: UNKNOWN
Author: Kyle Roux
Author-email: kyle@level2designs.com
License: UNKNOWN
Platform: UNKNOWN
